{
  "fetched": "2026-04-28T17:24:07Z",
  "week_ending": "2026-04-27",
  "total_head": 106000,
  "year_ago_head": 104267,
  "pct_of_year_ago": 101.7,
  "steer_head": null,
  "heifer_head": null,
  "cow_head": null,
  "ytd_head": 8725600,
  "ytd_year_ago": 9667508,
  "ytd_pct": -9.7,
  "daily": {
    "date": "2026-04-27",
    "cattle": 106000,
    "week_ago": 97000,
    "year_ago": 104267,
    "wtd": 106000,
    "ytd": 8725600,
    "ytd_year_ago": 9667508,
    "ytd_pct": -9.7,
    "breakdown": {
      "steers_heifers": 74000,
      "cows_bulls": 19000
    }
  },
  "source": "ams_3208_daily_pdf"
}